adafruit_ahtx0.py
adafruit_circuitpython_ahtx0-1.0.27.dist-info/licenses/LICENSE
adafruit_circuitpython_ahtx0-1.0.27.dist-info/METADATA
adafruit_circuitpython_ahtx0-1.0.27.dist-info/WHEEL
adafruit_circuitpython_ahtx0-1.0.27.dist-info/top_level.txt
adafruit_circuitpython_ahtx0-1.0.27.dist-info/RECORD
